datasource/__init__.py
datasource/earning.py
datasource/equity_list.py
datasource/price.py
datasource/treasury.py
datasource/util.py
dw_datasource-0.3.dist-info/METADATA
dw_datasource-0.3.dist-info/RECORD
dw_datasource-0.3.dist-info/WHEEL
dw_datasource-0.3.dist-info/top_level.txt
